vecops/__init__.py
vecops/addition.py
vecops/distance.py
vecops/inverse.py
vecops/length.py
vecops/multiplication.py
vecops/reflection.py
vecops/rotation.py
vecops/scale.py
vecops/subtraction.py
vecops/translation.py
vecops-1.2.3.dist-info/METADATA
vecops-1.2.3.dist-info/WHEEL
vecops-1.2.3.dist-info/licenses/LICENSE
vecops-1.2.3.dist-info/RECORD
